dargus/__init__.py
dargus/argus.py
dargus/argus_cli.py
dargus/argus_config.py
dargus/argus_exceptions.py
dargus/step.py
dargus/suite.py
dargus/test.py
dargus/utils.py
dargus/validation_result.py
dargus/validator.py
dargus-1.5.0.dist-info/LICENSE
dargus-1.5.0.dist-info/METADATA
dargus-1.5.0.dist-info/WHEEL
dargus-1.5.0.dist-info/entry_points.txt
dargus-1.5.0.dist-info/top_level.txt
dargus-1.5.0.dist-info/RECORD
