Metadata-Version: 2.1
Name: dargus
Version: 1.5.0
Summary: A Python engine for testing and benchmarking REST web services
Author-email: Daniel Perez-Gil <daniel.perez@zettagenomics.com>
Maintainer-email: Daniel Perez-Gil <daniel.perez@zettagenomics.com>
License: Apache License
Project-URL: Homepage, https://github.com/opencb/argus
Keywords: opencb,argus,dargus,rest,webservices,testing
Classifier: Development Status :: 4 - Beta
Classifier: Intended Audience :: Developers
Classifier: Topic :: Software Development :: Testing
Classifier: License :: OSI Approved :: Apache Software License
Classifier: Programming Language :: Python :: 3.6
Requires-Python: >=3.6
License-File: LICENSE
Requires-Dist: requests >=2.28.2
Requires-Dist: pyyaml >=6.0
Requires-Dist: json2html >=1.3.0
Requires-Dist: seaborn >=0.13.2
Requires-Dist: scipy >=1.12.0
Requires-Dist: pandas >=2.2.0
Requires-Dist: numpy >=1.26.4
Requires-Dist: matplotlib >=3.8.3
